monerorequest/__init__.py
monerorequest/check.py
monerorequest/cron_validation.py
monerorequest/decode.py
monerorequest/encode.py
monerorequest/monerorequest.py
monerorequest/request.py
monerorequest/request_v1.py
monerorequest/request_v2.py
monerorequest-2.1.0.dist-info/licenses/LICENSE
monerorequest-2.1.0.dist-info/METADATA
monerorequest-2.1.0.dist-info/WHEEL
monerorequest-2.1.0.dist-info/top_level.txt
monerorequest-2.1.0.dist-info/RECORD
