Metadata-Version: 2.4
Name: monerorequest
Version: 2.1.0
Summary: monerorequest is an easy way to create/decode Monero Payment Requests.
Home-page: https://github.com/lukeprofits/monerorequest
Author: Luke Profits
Classifier: Programming Language :: Python :: 3
Classifier: License :: OSI Approved :: MIT License
Classifier: Operating System :: OS Independent
License-File: LICENSE
Dynamic: author
Dynamic: classifier
Dynamic: home-page
Dynamic: license-file
Dynamic: summary
